{
    "version": "0.11.2",
    "architecture": {
        "32bit": {
            "url": "https://github.com/brittonhayes/pillager/releases/download/v0.11.2/pillager_0.11.2_windows_386.tar.gz",
            "bin": [
                "pillager.exe"
            ],
            "hash": "fd2e3c2838f43952e4b1d01f7711263c84f264c7456ccd500e03df4ae5633614"
        },
        "64bit": {
            "url": "https://github.com/brittonhayes/pillager/releases/download/v0.11.2/pillager_0.11.2_windows_amd64.tar.gz",
            "bin": [
                "pillager.exe"
            ],
            "hash": "9bf38bf140013d36888495af1415ddde340b0189ed5677bbb0465e48462ef3dc"
        },
        "arm64": {
            "url": "https://github.com/brittonhayes/pillager/releases/download/v0.11.2/pillager_0.11.2_windows_arm64.tar.gz",
            "bin": [
                "pillager.exe"
            ],
            "hash": "2587b9169ea8a80ee5f699eda8a80f694a5568bd5e2cb2a272a6548a335901fb"
        }
    },
    "homepage": "https://github.com/brittonhayes/pillager",
    "license": "MIT",
    "description": "Pillage filesystems for sensitive information"
}